{
  "ok": true,
  "generatedAt": "2026-07-08T16:24:06.618Z",
  "summary": {
    "ok": true,
    "rawLeads": 82,
    "qualified": 23,
    "working": 40,
    "contactable": 29,
    "realDecisionContacts": 61,
    "aLeads": 20,
    "a1Hot": 15,
    "a2Strong": 5,
    "salesReady": 3,
    "platformContactLeaks": 0,
    "platformBestContactLeaks": 0,
    "highValueNoContact": 0,
    "identityTrailCoverage": 5,
    "websiteOnlyContacts": 0,
    "duplicateLike": 0,
    "uniqueKeys": 82,
    "enrichmentDueNow": 68,
    "enrichedLastHour": 1,
    "enrichedLast24h": 1,
    "harvesters": 9,
    "harvesterRawSeen": 0,
    "harvesterSavedThisCycle": 0,
    "providerErrors": 0,
    "providerErrorsPerSaved": null,
    "salesReadyYield": 0.037,
    "salesReadyPerProviderError": null,
    "staleWorkers": [],
    "issues": []
  },
  "health": {
    "ok": true,
    "updatedAt": "2026-07-08T16:24:06.401Z",
    "counts": {
      "raw": 82,
      "qualified": 23,
      "working": 40,
      "contactable": 29,
      "aLeads": 20,
      "a1Hot": 15,
      "a2Strong": 5,
      "bNurture": 7,
      "cResearch": 13,
      "sourceOnly": 0
    },
    "duplicate": {
      "duplicateLike": 0,
      "uniqueKeys": 82
    },
    "enrichmentQueue": {
      "stale": 12,
      "contactless": 20,
      "neverDeep": 0,
      "eligible": 69,
      "dueNow": 68,
      "rotationDue": 48,
      "enrichedLastHour": 1,
      "enrichedLast24h": 1,
      "oldestDeepAgeHours": 124.9,
      "running": 2
    },
    "tasks": {
      "source-harvester": {
        "pid": 29128,
        "running": true
      },
      "source-harvester-social": {
        "pid": 14076,
        "running": true
      },
      "source-harvester-specialist": {
        "pid": 23352,
        "running": true
      },
      "source-harvester-ecosystem": {
        "pid": 25860,
        "running": true
      },
      "source-harvester-linkedin": {
        "pid": 5848,
        "running": true
      },
      "source-harvester-instagram": {
        "pid": 28756,
        "running": true
      },
      "source-harvester-platforms": {
        "pid": 7320,
        "running": true
      },
      "source-harvester-communities": {
        "pid": 31592,
        "running": true
      },
      "source-harvester-events": {
        "pid": 27244,
        "running": true
      },
      "enrichment-worker": {
        "pid": 25796,
        "running": true
      },
      "smart-enrichment-worker": {
        "pid": 3532,
        "running": true
      },
      "contact-gap-worker": {
        "pid": 9460,
        "running": true
      },
      "lead-cleaner": {
        "pid": 17168,
        "running": true
      },
      "qualified-exporter": {
        "pid": 12368,
        "running": true
      },
      "ui-snapshot-worker": {
        "pid": 20716,
        "running": true
      },
      "cloud-logger-worker": {
        "pid": 12460,
        "running": true
      },
      "supervisor": {
        "pid": 12660,
        "running": true
      }
    },
    "statuses": {
      "source-harvester": {
        "exists": true,
        "updatedAt": "2026-07-08T16:24:04.877Z",
        "ageMs": 1518,
        "status": {
          "status": "running",
          "workerName": "source-harvester",
          "phase": "scan",
          "cycle": 1,
          "options": {
            "limitPerQuery": 10,
            "maxQueries": 120,
            "fetchPages": true,
            "deepEnrich": true,
            "searchContacts": true,
            "queryOffset": 0,
            "includePartners": true,
            "includeRecruitment": true,
            "includeIntentPosts": true,
            "includeEcosystem": true,
            "includeSocialProfiles": true,
            "includeForums": true,
            "includeSpecialistSources": true,
            "includeYouTube": false,
            "regionSet": "global",
            "delayMs": 6500,
            "queryOffsetBase": 0,
            "maxCycles": 0,
            "maxContactPages": 6,
            "maxExternalWebsites": 5,
            "maxTrailQueries": 16,
            "trailLimit": 6,
            "exportEvery": 5,
            "incremental": true,
            "onlyIntents": "partner,intent",
            "onlyChannels": ""
          },
          "totals": {
            "total": 0,
            "exported": 0
          },
          "heartbeatAt": "2026-07-08T16:24:04.852Z",
          "progress": {
            "message": "Starting quality discovery with 120 queries",
            "status": "running",
            "latestLead": null,
            "sourceStats": {
              "linkedin": {
                "searches": 1,
                "raw": 0,
                "qualified": 0,
                "saved": 0,
                "discarded": 0,
                "duplicates": 0,
                "errors": 0,
                "providerErrors": 0,
                "reasons": {}
              }
            }
          },
          "updatedAt": "2026-07-08T16:24:04.877Z"
        }
      },
      "source-harvester-social": {
        "exists": true,
        "updatedAt": "2026-07-08T16:24:04.871Z",
        "ageMs": 1524,
        "status": {
          "status": "running",
          "workerName": "source-harvester-social",
          "phase": "scan",
          "cycle": 1,
          "options": {
            "limitPerQuery": 10,
            "maxQueries": 120,
            "fetchPages": true,
            "deepEnrich": true,
            "searchContacts": true,
            "queryOffset": 3000,
            "includePartners": true,
            "includeRecruitment": true,
            "includeIntentPosts": true,
            "includeEcosystem": true,
            "includeSocialProfiles": true,
            "includeForums": true,
            "includeSpecialistSources": true,
            "includeYouTube": false,
            "regionSet": "global",
            "delayMs": 7000,
            "queryOffsetBase": 3000,
            "maxCycles": 0,
            "maxContactPages": 6,
            "maxExternalWebsites": 5,
            "maxTrailQueries": 16,
            "trailLimit": 6,
            "exportEvery": 5,
            "incremental": true,
            "onlyIntents": "social",
            "onlyChannels": ""
          },
          "totals": {
            "total": 0,
            "exported": 0
          },
          "heartbeatAt": "2026-07-08T16:24:04.851Z",
          "progress": {
            "message": "Starting quality discovery with 120 queries",
            "status": "running",
            "latestLead": null,
            "sourceStats": {
              "linkedin": {
                "searches": 1,
                "raw": 0,
                "qualified": 0,
                "saved": 0,
                "discarded": 0,
                "duplicates": 0,
                "errors": 0,
                "providerErrors": 0,
                "reasons": {}
              }
            }
          },
          "updatedAt": "2026-07-08T16:24:04.871Z"
        }
      },
      "source-harvester-specialist": {
        "exists": true,
        "updatedAt": "2026-07-08T16:24:04.871Z",
        "ageMs": 1525,
        "status": {
          "status": "running",
          "workerName": "source-harvester-specialist",
          "phase": "scan",
          "cycle": 1,
          "options": {
            "limitPerQuery": 10,
            "maxQueries": 120,
            "fetchPages": true,
            "deepEnrich": true,
            "searchContacts": true,
            "queryOffset": 6000,
            "includePartners": true,
            "includeRecruitment": true,
            "includeIntentPosts": true,
            "includeEcosystem": true,
            "includeSocialProfiles": true,
            "includeForums": true,
            "includeSpecialistSources": true,
            "includeYouTube": false,
            "regionSet": "global",
            "delayMs": 7200,
            "queryOffsetBase": 6000,
            "maxCycles": 0,
            "maxContactPages": 6,
            "maxExternalWebsites": 5,
            "maxTrailQueries": 16,
            "trailLimit": 6,
            "exportEvery": 5,
            "incremental": true,
            "onlyIntents": "specialist,forum",
            "onlyChannels": ""
          },
          "totals": {
            "total": 0,
            "exported": 0
          },
          "heartbeatAt": "2026-07-08T16:24:04.849Z",
          "progress": {
            "message": "Starting quality discovery with 120 queries",
            "status": "running",
            "latestLead": null,
            "sourceStats": {
              "linkedin": {
                "searches": 1,
                "raw": 0,
                "qualified": 0,
                "saved": 0,
                "discarded": 0,
                "duplicates": 0,
                "errors": 0,
                "providerErrors": 0,
                "reasons": {}
              }
            }
          },
          "updatedAt": "2026-07-08T16:24:04.871Z"
        }
      },
      "source-harvester-ecosystem": {
        "exists": true,
        "updatedAt": "2026-07-08T16:24:04.871Z",
        "ageMs": 1525,
        "status": {
          "status": "running",
          "workerName": "source-harvester-ecosystem",
          "phase": "scan",
          "cycle": 1,
          "options": {
            "limitPerQuery": 8,
            "maxQueries": 90,
            "fetchPages": true,
            "deepEnrich": true,
            "searchContacts": true,
            "queryOffset": 9000,
            "includePartners": true,
            "includeRecruitment": true,
            "includeIntentPosts": true,
            "includeEcosystem": true,
            "includeSocialProfiles": true,
            "includeForums": true,
            "includeSpecialistSources": true,
            "includeYouTube": false,
            "regionSet": "global",
            "delayMs": 7800,
            "queryOffsetBase": 9000,
            "maxCycles": 0,
            "maxContactPages": 6,
            "maxExternalWebsites": 5,
            "maxTrailQueries": 14,
            "trailLimit": 5,
            "exportEvery": 5,
            "incremental": true,
            "onlyIntents": "ecosystem,recruitment",
            "onlyChannels": ""
          },
          "totals": {
            "total": 0,
            "exported": 0
          },
          "heartbeatAt": "2026-07-08T16:24:04.849Z",
          "progress": {
            "message": "Starting quality discovery with 90 queries",
            "status": "running",
            "latestLead": null,
            "sourceStats": {
              "linkedin": {
                "searches": 1,
                "raw": 0,
                "qualified": 0,
                "saved": 0,
                "discarded": 0,
                "duplicates": 0,
                "errors": 0,
                "providerErrors": 0,
                "reasons": {}
              }
            }
          },
          "updatedAt": "2026-07-08T16:24:04.871Z"
        }
      },
      "source-harvester-linkedin": {
        "exists": true,
        "updatedAt": "2026-07-08T16:24:04.893Z",
        "ageMs": 1503,
        "status": {
          "status": "running",
          "workerName": "source-harvester-linkedin",
          "phase": "scan",
          "cycle": 1,
          "options": {
            "limitPerQuery": 12,
            "maxQueries": 180,
            "fetchPages": true,
            "deepEnrich": true,
            "searchContacts": true,
            "queryOffset": 12000,
            "includePartners": true,
            "includeRecruitment": true,
            "includeIntentPosts": true,
            "includeEcosystem": true,
            "includeSocialProfiles": true,
            "includeForums": true,
            "includeSpecialistSources": true,
            "includeYouTube": false,
            "regionSet": "global",
            "delayMs": 6500,
            "queryOffsetBase": 12000,
            "maxCycles": 0,
            "maxContactPages": 7,
            "maxExternalWebsites": 6,
            "maxTrailQueries": 18,
            "trailLimit": 7,
            "exportEvery": 5,
            "incremental": true,
            "onlyIntents": "",
            "onlyChannels": "linkedin"
          },
          "totals": {
            "total": 0,
            "exported": 0
          },
          "heartbeatAt": "2026-07-08T16:24:04.879Z",
          "progress": {
            "message": "Starting quality discovery with 180 queries",
            "status": "running",
            "latestLead": null,
            "sourceStats": {
              "linkedin": {
                "searches": 1,
                "raw": 0,
                "qualified": 0,
                "saved": 0,
                "discarded": 0,
                "duplicates": 0,
                "errors": 0,
                "providerErrors": 0,
                "reasons": {}
              }
            }
          },
          "updatedAt": "2026-07-08T16:24:04.893Z"
        }
      },
      "source-harvester-instagram": {
        "exists": true,
        "updatedAt": "2026-07-08T16:24:04.871Z",
        "ageMs": 1526,
        "status": {
          "status": "running",
          "workerName": "source-harvester-instagram",
          "phase": "scan",
          "cycle": 1,
          "options": {
            "limitPerQuery": 12,
            "maxQueries": 180,
            "fetchPages": true,
            "deepEnrich": true,
            "searchContacts": true,
            "queryOffset": 15000,
            "includePartners": true,
            "includeRecruitment": true,
            "includeIntentPosts": true,
            "includeEcosystem": true,
            "includeSocialProfiles": true,
            "includeForums": true,
            "includeSpecialistSources": true,
            "includeYouTube": false,
            "regionSet": "global",
            "delayMs": 6800,
            "queryOffsetBase": 15000,
            "maxCycles": 0,
            "maxContactPages": 7,
            "maxExternalWebsites": 6,
            "maxTrailQueries": 18,
            "trailLimit": 7,
            "exportEvery": 5,
            "incremental": true,
            "onlyIntents": "",
            "onlyChannels": "instagram"
          },
          "totals": {
            "total": 0,
            "exported": 0
          },
          "heartbeatAt": "2026-07-08T16:24:04.852Z",
          "progress": {
            "message": "Starting quality discovery with 45 queries",
            "status": "running",
            "latestLead": null,
            "sourceStats": {
              "instagram": {
                "searches": 1,
                "raw": 0,
                "qualified": 0,
                "saved": 0,
                "discarded": 0,
                "duplicates": 0,
                "errors": 0,
                "providerErrors": 0,
                "reasons": {}
              }
            }
          },
          "updatedAt": "2026-07-08T16:24:04.871Z"
        }
      },
      "source-harvester-platforms": {
        "exists": true,
        "updatedAt": "2026-07-08T16:24:04.871Z",
        "ageMs": 1526,
        "status": {
          "status": "running",
          "workerName": "source-harvester-platforms",
          "phase": "scan",
          "cycle": 1,
          "options": {
            "limitPerQuery": 10,
            "maxQueries": 160,
            "fetchPages": true,
            "deepEnrich": true,
            "searchContacts": true,
            "queryOffset": 18000,
            "includePartners": true,
            "includeRecruitment": true,
            "includeIntentPosts": true,
            "includeEcosystem": true,
            "includeSocialProfiles": true,
            "includeForums": true,
            "includeSpecialistSources": true,
            "includeYouTube": false,
            "regionSet": "global",
            "delayMs": 7800,
            "queryOffsetBase": 18000,
            "maxCycles": 0,
            "maxContactPages": 7,
            "maxExternalWebsites": 6,
            "maxTrailQueries": 18,
            "trailLimit": 7,
            "exportEvery": 5,
            "incremental": true,
            "onlyIntents": "",
            "onlyChannels": "myfxbook,mql5,specialist",
            "maxMql5QueryShare": "0.4",
            "minMql5Queries": "20"
          },
          "totals": {
            "total": 0,
            "exported": 0
          },
          "heartbeatAt": "2026-07-08T16:24:04.848Z",
          "progress": {
            "message": "Starting quality discovery with 47 queries",
            "status": "running",
            "latestLead": null,
            "sourceStats": {
              "myfxbook": {
                "searches": 1,
                "raw": 0,
                "qualified": 0,
                "saved": 0,
                "discarded": 0,
                "duplicates": 0,
                "errors": 0,
                "providerErrors": 0,
                "reasons": {}
              }
            }
          },
          "updatedAt": "2026-07-08T16:24:04.871Z"
        }
      },
      "source-harvester-communities": {
        "exists": true,
        "updatedAt": "2026-07-08T16:24:04.896Z",
        "ageMs": 1501,
        "status": {
          "status": "running",
          "workerName": "source-harvester-communities",
          "phase": "scan",
          "cycle": 1,
          "options": {
            "limitPerQuery": 12,
            "maxQueries": 180,
            "fetchPages": true,
            "deepEnrich": true,
            "searchContacts": true,
            "queryOffset": 21000,
            "includePartners": true,
            "includeRecruitment": true,
            "includeIntentPosts": true,
            "includeEcosystem": true,
            "includeSocialProfiles": true,
            "includeForums": true,
            "includeSpecialistSources": true,
            "includeYouTube": false,
            "regionSet": "global",
            "delayMs": 7200,
            "queryOffsetBase": 21000,
            "maxCycles": 0,
            "maxContactPages": 7,
            "maxExternalWebsites": 6,
            "maxTrailQueries": 18,
            "trailLimit": 7,
            "exportEvery": 5,
            "incremental": true,
            "onlyIntents": "",
            "onlyChannels": "telegram,discord,forum,x,tiktok,facebook_threads"
          },
          "totals": {
            "total": 0,
            "exported": 0
          },
          "heartbeatAt": "2026-07-08T16:24:04.881Z",
          "progress": {
            "message": "Starting quality discovery with 116 queries",
            "status": "running",
            "latestLead": null,
            "sourceStats": {
              "telegram": {
                "searches": 1,
                "raw": 0,
                "qualified": 0,
                "saved": 0,
                "discarded": 0,
                "duplicates": 0,
                "errors": 0,
                "providerErrors": 0,
                "reasons": {}
              }
            }
          },
          "updatedAt": "2026-07-08T16:24:04.896Z"
        }
      },
      "source-harvester-events": {
        "exists": true,
        "updatedAt": "2026-07-08T16:24:04.873Z",
        "ageMs": 1525,
        "status": {
          "status": "running",
          "workerName": "source-harvester-events",
          "phase": "scan",
          "cycle": 1,
          "options": {
            "limitPerQuery": 10,
            "maxQueries": 120,
            "fetchPages": true,
            "deepEnrich": true,
            "searchContacts": true,
            "queryOffset": 24000,
            "includePartners": true,
            "includeRecruitment": true,
            "includeIntentPosts": true,
            "includeEcosystem": true,
            "includeSocialProfiles": true,
            "includeForums": true,
            "includeSpecialistSources": true,
            "includeYouTube": false,
            "regionSet": "global",
            "delayMs": 7600,
            "queryOffsetBase": 24000,
            "maxCycles": 0,
            "maxContactPages": 7,
            "maxExternalWebsites": 6,
            "maxTrailQueries": 16,
            "trailLimit": 6,
            "exportEvery": 5,
            "incremental": true,
            "onlyIntents": "",
            "onlyChannels": "ecosystem,recruitment"
          },
          "totals": {
            "total": 0,
            "exported": 0
          },
          "heartbeatAt": "2026-07-08T16:24:04.855Z",
          "progress": {
            "message": "Starting quality discovery with 120 queries",
            "status": "running",
            "latestLead": null,
            "sourceStats": {
              "ecosystem": {
                "searches": 1,
                "raw": 0,
                "qualified": 0,
                "saved": 0,
                "discarded": 0,
                "duplicates": 0,
                "errors": 0,
                "providerErrors": 0,
                "reasons": {}
              }
            }
          },
          "updatedAt": "2026-07-08T16:24:04.873Z"
        }
      },
      "enrichment-worker": {
        "exists": true,
        "updatedAt": "2026-07-08T16:24:05.319Z",
        "ageMs": 1079,
        "status": {
          "status": "running",
          "phase": "enriching",
          "options": {
            "delayMs": 4500,
            "idleMs": 9000,
            "staleHours": 8,
            "hotStaleHours": 1.5,
            "contactlessStaleHours": 1.5,
            "rotationHours": 3,
            "maxContactPages": 7,
            "maxExternalWebsites": 6,
            "maxTrailQueries": 18,
            "trailLimit": 7
          },
          "processed": 0,
          "rejected": 0,
          "errors": 0,
          "idleCycles": 0,
          "queue": {
            "eligible": 69,
            "dueNow": 69,
            "never": 0,
            "contactlessDue": 56,
            "scheduledDue": 13,
            "rotationDue": 0,
            "recentlyEnriched1h": 0,
            "recentlyEnriched24h": 0,
            "blockedRunning": 1,
            "blockedNoise": 0,
            "oldestDeepAgeHours": 39.7
          },
          "current": {
            "id": "ea9e014f6f428d8b",
            "name": "Attending the Money Expo at the Jio Convention Centre ...",
            "url": "https://www.linkedin.com/posts/deepjyoti-dutta-dd11022003_attending-the-money-expo-at-the-jio-convention-activity-7366762448424460289-CzkY",
            "platform": "LinkedIn",
            "dueReason": "contactless_due"
          },
          "updatedAt": "2026-07-08T16:24:05.319Z"
        }
      },
      "smart-enrichment-worker": {
        "exists": true,
        "updatedAt": "2026-07-08T16:24:05.454Z",
        "ageMs": 944,
        "status": {
          "status": "running",
          "phase": "smart-enriching",
          "processed": 0,
          "stored": 0,
          "rejected": 0,
          "errors": 0,
          "current": {
            "id": "aab6e3425505871d",
            "name": "Prices",
            "url": "https://finviz.com/forex",
            "platform": "Web",
            "bucket": "telegram"
          },
          "lastResult": null,
          "updatedAt": "2026-07-08T16:24:05.454Z"
        }
      },
      "contact-gap-worker": {
        "exists": true,
        "updatedAt": "2026-07-08T16:24:04.911Z",
        "ageMs": 1487,
        "status": {
          "status": "running",
          "phase": "enriching-gap",
          "processed": 0,
          "stored": 0,
          "rejected": 0,
          "errors": 0,
          "current": {
            "id": "b9875250ff0beebd",
            "name": "Forex Fund Manager Forex System by Forex Trader supportfx",
            "url": "https://www.myfxbook.com/members/supportfx/forex-fund-manager/3593761",
            "bucket": "myfxbook",
            "score": 234
          },
          "lastResult": null,
          "updatedAt": "2026-07-08T16:24:04.911Z"
        }
      },
      "lead-cleaner": {
        "exists": true,
        "updatedAt": "2026-07-08T16:24:03.658Z",
        "ageMs": 2741,
        "status": {
          "status": "running",
          "phase": "waiting",
          "cycle": 1,
          "intervalMs": 90000,
          "limit": 1000,
          "totalRemoved": 0,
          "errors": 0,
          "lastRun": {
            "ok": true,
            "dryRun": false,
            "before": 82,
            "removed": 0,
            "after": 82,
            "backupPath": null,
            "byReason": {},
            "sample": [],
            "exported": null
          },
          "updatedAt": "2026-07-08T16:24:03.658Z"
        }
      },
      "qualified-exporter": {
        "exists": true,
        "updatedAt": "2026-07-08T16:24:03.944Z",
        "ageMs": 2455,
        "status": {
          "status": "running",
          "intervalMs": 90000,
          "lastExport": {
            "csvPath": "C:\\Users\\steve\\bd-lead-engine\\autopilot-qualified-leads.csv",
            "jsonPath": "C:\\Users\\steve\\bd-lead-engine\\autopilot-qualified-leads.json",
            "contactCsvPath": "C:\\Users\\steve\\bd-lead-engine\\autopilot-qualified-contactable-leads.csv",
            "contactJsonPath": "C:\\Users\\steve\\bd-lead-engine\\autopilot-qualified-contactable-leads.json",
            "hotCsvPath": "C:\\Users\\steve\\bd-lead-engine\\autopilot-hot-leads.csv",
            "hotJsonPath": "C:\\Users\\steve\\bd-lead-engine\\autopilot-hot-leads.json",
            "socialCsvPath": "C:\\Users\\steve\\bd-lead-engine\\autopilot-social-leads.csv",
            "socialJsonPath": "C:\\Users\\steve\\bd-lead-engine\\autopilot-social-leads.json",
            "instagramCsvPath": "C:\\Users\\steve\\bd-lead-engine\\autopilot-instagram-leads.csv",
            "instagramJsonPath": "C:\\Users\\steve\\bd-lead-engine\\autopilot-instagram-leads.json",
            "linkedinCsvPath": "C:\\Users\\steve\\bd-lead-engine\\autopilot-linkedin-leads.csv",
            "linkedinJsonPath": "C:\\Users\\steve\\bd-lead-engine\\autopilot-linkedin-leads.json",
            "xCsvPath": "C:\\Users\\steve\\bd-lead-engine\\autopilot-x-leads.csv",
            "xJsonPath": "C:\\Users\\steve\\bd-lead-engine\\autopilot-x-leads.json",
            "workingCsvPath": "C:\\Users\\steve\\bd-lead-engine\\autopilot-working-leads.csv",
            "workingJsonPath": "C:\\Users\\steve\\bd-lead-engine\\autopilot-working-leads.json",
            "researchCsvPath": "C:\\Users\\steve\\bd-lead-engine\\autopilot-research-sources.csv",
            "researchJsonPath": "C:\\Users\\steve\\bd-lead-engine\\autopilot-research-sources.json",
            "exported": 23,
            "working": 40,
            "researchSources": 21,
            "contactable": 23,
            "hot": 19,
            "social": 21,
            "instagram": 0,
            "linkedin": 20,
            "x": 0,
            "total": 82
          },
          "updatedAt": "2026-07-08T16:24:03.944Z"
        }
      },
      "ui-snapshot-worker": {
        "exists": true,
        "updatedAt": "2026-07-08T16:24:03.781Z",
        "ageMs": 2618,
        "status": {
          "ok": true,
          "updatedAt": "2026-07-08T16:24:03.781Z",
          "total": 57,
          "rawTotal": 82,
          "rejectedTotal": 25,
          "buildMs": 126,
          "qualityGate": "commercial-noise-policy-v3"
        }
      },
      "cloud-logger-worker": {
        "exists": true,
        "updatedAt": "2026-07-08T16:24:06.174Z",
        "ageMs": 226,
        "status": {
          "status": "running",
          "phase": "started",
          "intervalMs": 600000,
          "loop": false,
          "once": true,
          "updatedAt": "2026-07-08T16:24:06.174Z"
        }
      },
      "supervisor": {
        "exists": true,
        "updatedAt": "2026-07-08T16:24:04.109Z",
        "ageMs": 2291,
        "status": {
          "status": "running",
          "cycle": 1,
          "intervalMs": 60000,
          "ensured": [
            {
              "name": "source-harvester",
              "pid": 29128,
              "status": "started"
            },
            {
              "name": "source-harvester-social",
              "pid": 14076,
              "status": "started"
            },
            {
              "name": "source-harvester-specialist",
              "pid": 23352,
              "status": "started"
            },
            {
              "name": "source-harvester-ecosystem",
              "pid": 25860,
              "status": "started"
            },
            {
              "name": "source-harvester-linkedin",
              "pid": 5848,
              "status": "started"
            },
            {
              "name": "source-harvester-instagram",
              "pid": 28756,
              "status": "started"
            },
            {
              "name": "source-harvester-platforms",
              "pid": 7320,
              "status": "started"
            },
            {
              "name": "source-harvester-communities",
              "pid": 31592,
              "status": "started"
            },
            {
              "name": "source-harvester-events",
              "pid": 27244,
              "status": "started"
            },
            {
              "name": "enrichment-worker",
              "pid": 25796,
              "status": "running"
            },
            {
              "name": "smart-enrichment-worker",
              "pid": 3532,
              "status": "running"
            },
            {
              "name": "contact-gap-worker",
              "pid": 9460,
              "status": "started"
            },
            {
              "name": "lead-cleaner",
              "pid": 17168,
              "status": "running"
            },
            {
              "name": "qualified-exporter",
              "pid": 12368,
              "status": "running"
            },
            {
              "name": "ui-snapshot-worker",
              "pid": 20716,
              "status": "running"
            },
            {
              "name": "cloud-logger-worker",
              "pid": 12460,
              "status": "started"
            }
          ],
          "exportResult": null,
          "health": {
            "ok": true,
            "counts": {
              "raw": 82,
              "qualified": 23,
              "working": 40,
              "contactable": 29,
              "aLeads": 20,
              "a1Hot": 15,
              "a2Strong": 5,
              "bNurture": 7,
              "cResearch": 13,
              "sourceOnly": 0
            },
            "enrichmentQueue": {
              "stale": 12,
              "contactless": 20,
              "neverDeep": 0,
              "eligible": 69,
              "dueNow": 69,
              "rotationDue": 49,
              "enrichedLastHour": 0,
              "enrichedLast24h": 0,
              "oldestDeepAgeHours": 124.9,
              "running": 0
            },
            "issues": [
              {
                "severity": "warning",
                "code": "source-harvester_stale_status",
                "message": "source-harvester status is stale."
              },
              {
                "severity": "warning",
                "code": "source-harvester-social_stale_status",
                "message": "source-harvester-social status is stale."
              },
              {
                "severity": "warning",
                "code": "source-harvester-specialist_stale_status",
                "message": "source-harvester-specialist status is stale."
              },
              {
                "severity": "warning",
                "code": "source-harvester-ecosystem_stale_status",
                "message": "source-harvester-ecosystem status is stale."
              },
              {
                "severity": "warning",
                "code": "source-harvester-linkedin_stale_status",
                "message": "source-harvester-linkedin status is stale."
              },
              {
                "severity": "warning",
                "code": "source-harvester-instagram_stale_status",
                "message": "source-harvester-instagram status is stale."
              },
              {
                "severity": "warning",
                "code": "source-harvester-platforms_stale_status",
                "message": "source-harvester-platforms status is stale."
              },
              {
                "severity": "warning",
                "code": "source-harvester-communities_stale_status",
                "message": "source-harvester-communities status is stale."
              },
              {
                "severity": "warning",
                "code": "source-harvester-events_stale_status",
                "message": "source-harvester-events status is stale."
              },
              {
                "severity": "warning",
                "code": "enrichment-worker_stale_status",
                "message": "enrichment-worker status is stale."
              },
              {
                "severity": "warning",
                "code": "smart-enrichment-worker_stale_status",
                "message": "smart-enrichment-worker status is stale."
              },
              {
                "severity": "warning",
                "code": "contact-gap-worker_stale_status",
                "message": "contact-gap-worker status is stale."
              }
            ]
          },
          "updatedAt": "2026-07-08T16:24:04.109Z"
        }
      }
    },
    "exports": {
      "autopilot-qualified-leads.csv": {
        "exists": true,
        "path": "C:\\Users\\steve\\bd-lead-engine\\autopilot-qualified-leads.csv",
        "size": 59694,
        "updatedAt": "2026-07-08T16:24:03.840Z",
        "ageMs": 2560.30615234375
      },
      "autopilot-qualified-contactable-leads.csv": {
        "exists": true,
        "path": "C:\\Users\\steve\\bd-lead-engine\\autopilot-qualified-contactable-leads.csv",
        "size": 59694,
        "updatedAt": "2026-07-08T16:24:03.854Z",
        "ageMs": 2546.305908203125
      },
      "autopilot-hot-leads.csv": {
        "exists": true,
        "path": "C:\\Users\\steve\\bd-lead-engine\\autopilot-hot-leads.csv",
        "size": 46126,
        "updatedAt": "2026-07-08T16:24:03.866Z",
        "ageMs": 2535.306884765625
      },
      "autopilot-working-leads.csv": {
        "exists": true,
        "path": "C:\\Users\\steve\\bd-lead-engine\\autopilot-working-leads.csv",
        "size": 95286,
        "updatedAt": "2026-07-08T16:24:05.577Z",
        "ageMs": 824.4423828125
      },
      "autopilot-social-leads.csv": {
        "exists": true,
        "path": "C:\\Users\\steve\\bd-lead-engine\\autopilot-social-leads.csv",
        "size": 49849,
        "updatedAt": "2026-07-08T16:24:05.547Z",
        "ageMs": 854.443603515625
      },
      "autopilot-linkedin-leads.csv": {
        "exists": true,
        "path": "C:\\Users\\steve\\bd-lead-engine\\autopilot-linkedin-leads.csv",
        "size": 48699,
        "updatedAt": "2026-07-08T16:24:05.555Z",
        "ageMs": 846.442626953125
      },
      "autopilot-instagram-leads.csv": {
        "exists": true,
        "path": "C:\\Users\\steve\\bd-lead-engine\\autopilot-instagram-leads.csv",
        "size": 482,
        "updatedAt": "2026-07-08T16:24:05.550Z",
        "ageMs": 851.443115234375
      },
      "autopilot-x-leads.csv": {
        "exists": true,
        "path": "C:\\Users\\steve\\bd-lead-engine\\autopilot-x-leads.csv",
        "size": 482,
        "updatedAt": "2026-07-08T16:24:05.558Z",
        "ageMs": 843.443603515625
      }
    },
    "issues": []
  },
  "quality": {
    "totals": {
      "raw": 82,
      "exportQualified": 23,
      "qualified": 23,
      "working": 40,
      "realDecisionContacts": 61,
      "salesReady": 3,
      "platformContactLeaks": 0,
      "platformBestContactLeaks": 0,
      "highValueNoContact": 0,
      "identityTrailCoverage": 5,
      "websiteOnlyContacts": 0
    },
    "byBucket": {
      "linkedin": 39,
      "web": 15,
      "tiktok": 10,
      "recruitment": 6,
      "instagram": 3,
      "discord": 2,
      "ecosystem": 2,
      "facebook_threads": 1,
      "telegram": 1,
      "x": 1,
      "myfxbook": 1,
      "mql5": 1
    },
    "qualifiedByBucket": {
      "linkedin": 20,
      "tiktok": 2,
      "web": 1
    },
    "workingByBucket": {
      "linkedin": 24,
      "tiktok": 10,
      "web": 2,
      "x": 1,
      "telegram": 1,
      "instagram": 1,
      "recruitment": 1
    },
    "realDecisionContactsByBucket": {
      "linkedin": 37,
      "web": 15,
      "discord": 2,
      "tiktok": 2,
      "ecosystem": 2,
      "facebook_threads": 1,
      "telegram": 1,
      "x": 1
    },
    "salesReadyByBucket": {
      "tiktok": 2,
      "web": 1
    },
    "topSalesReady": [
      {
        "name": "underratedfx videoSouth African Forex Trader's Journey",
        "bucket": "tiktok",
        "score": 89,
        "contactScore": 60,
        "contact": "https://wa.me/0646709366"
      },
      {
        "name": "2025",
        "bucket": "web",
        "score": 99,
        "contactScore": 58,
        "contact": "https://www.facebook.com/forexteam"
      },
      {
        "name": "AU USD Gold Price Analysis & Live Chart",
        "bucket": "tiktok",
        "score": 93,
        "contactScore": 58,
        "contact": "https://twitter.com/xquantify"
      }
    ],
    "platformLeakSamples": [],
    "platformBestContactLeakSamples": [],
    "highValueNoContactSamples": [],
    "weakSpecialistSamples": [
      {
        "name": "Forex Fund Manager Forex System by Forex Trader supportfx",
        "bucket": "myfxbook",
        "score": 74,
        "contactScore": 0
      },
      {
        "name": "Nguyen Hang Hai Ha",
        "bucket": "mql5",
        "score": 73,
        "contactScore": 0
      }
    ],
    "websiteOnlyContactSamples": []
  },
  "workers": [
    {
      "name": "cloud-logger-worker",
      "status": "running",
      "phase": "started",
      "age": "0s",
      "ageMs": 233,
      "cycle": null,
      "pid": null,
      "message": "",
      "current": null,
      "lastResult": null,
      "counts": {
        "raw": 0,
        "saved": 0,
        "discarded": 0,
        "duplicates": 0,
        "providerErrors": 0,
        "total": null,
        "exported": null,
        "working": null,
        "contactable": null,
        "hot": null,
        "totalRemoved": null,
        "processed": null,
        "stored": null,
        "errors": null
      }
    },
    {
      "name": "contact-gap-worker",
      "status": "running",
      "phase": "enriching-gap",
      "age": "1s",
      "ageMs": 1496,
      "cycle": null,
      "pid": null,
      "message": "",
      "current": {
        "id": "b9875250ff0beebd",
        "name": "Forex Fund Manager Forex System by Forex Trader supportfx",
        "url": "https://www.myfxbook.com/members/supportfx/forex-fund-manager/3593761",
        "bucket": "myfxbook",
        "score": 234
      },
      "lastResult": null,
      "counts": {
        "raw": 0,
        "saved": 0,
        "discarded": 0,
        "duplicates": 0,
        "providerErrors": 0,
        "total": null,
        "exported": null,
        "working": null,
        "contactable": null,
        "hot": null,
        "totalRemoved": null,
        "processed": 0,
        "stored": 0,
        "errors": 0
      }
    },
    {
      "name": "engine-control",
      "status": "running",
      "phase": "started",
      "age": "10s",
      "ageMs": 9818,
      "cycle": null,
      "pid": null,
      "message": "",
      "current": null,
      "lastResult": null,
      "counts": {
        "raw": 0,
        "saved": 0,
        "discarded": 0,
        "duplicates": 0,
        "providerErrors": 0,
        "total": null,
        "exported": null,
        "working": null,
        "contactable": null,
        "hot": null,
        "totalRemoved": null,
        "processed": null,
        "stored": null,
        "errors": null
      }
    },
    {
      "name": "enrichment-worker",
      "status": "running",
      "phase": "enriching",
      "age": "1s",
      "ageMs": 1088,
      "cycle": null,
      "pid": null,
      "message": "",
      "current": {
        "id": "ea9e014f6f428d8b",
        "name": "Attending the Money Expo at the Jio Convention Centre ...",
        "url": "https://www.linkedin.com/posts/deepjyoti-dutta-dd11022003_attending-the-money-expo-at-the-jio-convention-activity-7366762448424460289-CzkY",
        "platform": "LinkedIn",
        "dueReason": "contactless_due"
      },
      "lastResult": null,
      "counts": {
        "raw": 0,
        "saved": 0,
        "discarded": 0,
        "duplicates": 0,
        "providerErrors": 0,
        "total": null,
        "exported": null,
        "working": null,
        "contactable": null,
        "hot": null,
        "totalRemoved": null,
        "processed": 0,
        "stored": null,
        "errors": 0
      }
    },
    {
      "name": "lead-cleaner",
      "status": "running",
      "phase": "waiting",
      "age": "3s",
      "ageMs": 2750,
      "cycle": 1,
      "pid": null,
      "message": "",
      "current": null,
      "lastResult": null,
      "counts": {
        "raw": 0,
        "saved": 0,
        "discarded": 0,
        "duplicates": 0,
        "providerErrors": 0,
        "total": null,
        "exported": null,
        "working": null,
        "contactable": null,
        "hot": null,
        "totalRemoved": 0,
        "processed": null,
        "stored": null,
        "errors": 0
      }
    },
    {
      "name": "qualified-exporter",
      "status": "running",
      "phase": "n/a",
      "age": "2s",
      "ageMs": 2464,
      "cycle": null,
      "pid": null,
      "message": "",
      "current": null,
      "lastResult": null,
      "counts": {
        "raw": 0,
        "saved": 0,
        "discarded": 0,
        "duplicates": 0,
        "providerErrors": 0,
        "total": 82,
        "exported": 23,
        "working": 40,
        "contactable": 23,
        "hot": 19,
        "totalRemoved": null,
        "processed": null,
        "stored": null,
        "errors": null
      }
    },
    {
      "name": "smart-enrichment-worker",
      "status": "running",
      "phase": "smart-enriching",
      "age": "1s",
      "ageMs": 954,
      "cycle": null,
      "pid": null,
      "message": "",
      "current": {
        "id": "aab6e3425505871d",
        "name": "Prices",
        "url": "https://finviz.com/forex",
        "platform": "Web",
        "bucket": "telegram"
      },
      "lastResult": null,
      "counts": {
        "raw": 0,
        "saved": 0,
        "discarded": 0,
        "duplicates": 0,
        "providerErrors": 0,
        "total": null,
        "exported": null,
        "working": null,
        "contactable": null,
        "hot": null,
        "totalRemoved": null,
        "processed": 0,
        "stored": 0,
        "errors": 0
      }
    },
    {
      "name": "source-harvester",
      "status": "running",
      "phase": "scan",
      "age": "2s",
      "ageMs": 1533,
      "cycle": 1,
      "pid": null,
      "message": "Starting quality discovery with 120 queries",
      "current": null,
      "lastResult": null,
      "counts": {
        "raw": 0,
        "saved": 0,
        "discarded": 0,
        "duplicates": 0,
        "providerErrors": 0,
        "total": 0,
        "exported": 0,
        "working": null,
        "contactable": null,
        "hot": null,
        "totalRemoved": null,
        "processed": null,
        "stored": null,
        "errors": null
      }
    },
    {
      "name": "source-harvester-communities",
      "status": "running",
      "phase": "scan",
      "age": "2s",
      "ageMs": 1512,
      "cycle": 1,
      "pid": null,
      "message": "Starting quality discovery with 116 queries",
      "current": null,
      "lastResult": null,
      "counts": {
        "raw": 0,
        "saved": 0,
        "discarded": 0,
        "duplicates": 0,
        "providerErrors": 0,
        "total": 0,
        "exported": 0,
        "working": null,
        "contactable": null,
        "hot": null,
        "totalRemoved": null,
        "processed": null,
        "stored": null,
        "errors": null
      }
    },
    {
      "name": "source-harvester-ecosystem",
      "status": "running",
      "phase": "scan",
      "age": "2s",
      "ageMs": 1537,
      "cycle": 1,
      "pid": null,
      "message": "Starting quality discovery with 90 queries",
      "current": null,
      "lastResult": null,
      "counts": {
        "raw": 0,
        "saved": 0,
        "discarded": 0,
        "duplicates": 0,
        "providerErrors": 0,
        "total": 0,
        "exported": 0,
        "working": null,
        "contactable": null,
        "hot": null,
        "totalRemoved": null,
        "processed": null,
        "stored": null,
        "errors": null
      }
    },
    {
      "name": "source-harvester-events",
      "status": "running",
      "phase": "scan",
      "age": "2s",
      "ageMs": 1536,
      "cycle": 1,
      "pid": null,
      "message": "Starting quality discovery with 120 queries",
      "current": null,
      "lastResult": null,
      "counts": {
        "raw": 0,
        "saved": 0,
        "discarded": 0,
        "duplicates": 0,
        "providerErrors": 0,
        "total": 0,
        "exported": 0,
        "working": null,
        "contactable": null,
        "hot": null,
        "totalRemoved": null,
        "processed": null,
        "stored": null,
        "errors": null
      }
    },
    {
      "name": "source-harvester-instagram",
      "status": "running",
      "phase": "scan",
      "age": "2s",
      "ageMs": 1538,
      "cycle": 1,
      "pid": null,
      "message": "Starting quality discovery with 45 queries",
      "current": null,
      "lastResult": null,
      "counts": {
        "raw": 0,
        "saved": 0,
        "discarded": 0,
        "duplicates": 0,
        "providerErrors": 0,
        "total": 0,
        "exported": 0,
        "working": null,
        "contactable": null,
        "hot": null,
        "totalRemoved": null,
        "processed": null,
        "stored": null,
        "errors": null
      }
    },
    {
      "name": "source-harvester-linkedin",
      "status": "running",
      "phase": "scan",
      "age": "2s",
      "ageMs": 1516,
      "cycle": 1,
      "pid": null,
      "message": "Starting quality discovery with 180 queries",
      "current": null,
      "lastResult": null,
      "counts": {
        "raw": 0,
        "saved": 0,
        "discarded": 0,
        "duplicates": 0,
        "providerErrors": 0,
        "total": 0,
        "exported": 0,
        "working": null,
        "contactable": null,
        "hot": null,
        "totalRemoved": null,
        "processed": null,
        "stored": null,
        "errors": null
      }
    },
    {
      "name": "source-harvester-platforms",
      "status": "running",
      "phase": "scan",
      "age": "2s",
      "ageMs": 1538,
      "cycle": 1,
      "pid": null,
      "message": "Starting quality discovery with 47 queries",
      "current": null,
      "lastResult": null,
      "counts": {
        "raw": 0,
        "saved": 0,
        "discarded": 0,
        "duplicates": 0,
        "providerErrors": 0,
        "total": 0,
        "exported": 0,
        "working": null,
        "contactable": null,
        "hot": null,
        "totalRemoved": null,
        "processed": null,
        "stored": null,
        "errors": null
      }
    },
    {
      "name": "source-harvester-social",
      "status": "running",
      "phase": "scan",
      "age": "2s",
      "ageMs": 1538,
      "cycle": 1,
      "pid": null,
      "message": "Starting quality discovery with 120 queries",
      "current": null,
      "lastResult": null,
      "counts": {
        "raw": 0,
        "saved": 0,
        "discarded": 0,
        "duplicates": 0,
        "providerErrors": 0,
        "total": 0,
        "exported": 0,
        "working": null,
        "contactable": null,
        "hot": null,
        "totalRemoved": null,
        "processed": null,
        "stored": null,
        "errors": null
      }
    },
    {
      "name": "source-harvester-specialist",
      "status": "running",
      "phase": "scan",
      "age": "2s",
      "ageMs": 1539,
      "cycle": 1,
      "pid": null,
      "message": "Starting quality discovery with 120 queries",
      "current": null,
      "lastResult": null,
      "counts": {
        "raw": 0,
        "saved": 0,
        "discarded": 0,
        "duplicates": 0,
        "providerErrors": 0,
        "total": 0,
        "exported": 0,
        "working": null,
        "contactable": null,
        "hot": null,
        "totalRemoved": null,
        "processed": null,
        "stored": null,
        "errors": null
      }
    },
    {
      "name": "supervisor",
      "status": "running",
      "phase": "n/a",
      "age": "2s",
      "ageMs": 2301,
      "cycle": 1,
      "pid": null,
      "message": "",
      "current": null,
      "lastResult": null,
      "counts": {
        "raw": 0,
        "saved": 0,
        "discarded": 0,
        "duplicates": 0,
        "providerErrors": 0,
        "total": null,
        "exported": null,
        "working": null,
        "contactable": null,
        "hot": null,
        "totalRemoved": null,
        "processed": null,
        "stored": null,
        "errors": null
      }
    },
    {
      "name": "ui-snapshot-worker",
      "status": "unknown",
      "phase": "n/a",
      "age": "3s",
      "ageMs": 2629,
      "cycle": null,
      "pid": null,
      "message": "",
      "current": null,
      "lastResult": null,
      "counts": {
        "raw": 0,
        "saved": 0,
        "discarded": 0,
        "duplicates": 0,
        "providerErrors": 0,
        "total": null,
        "exported": null,
        "working": null,
        "contactable": null,
        "hot": null,
        "totalRemoved": null,
        "processed": null,
        "stored": null,
        "errors": null
      }
    }
  ],
  "exports": {
    "autopilot-qualified-leads.csv": {
      "exists": true,
      "path": "C:\\Users\\steve\\bd-lead-engine\\autopilot-qualified-leads.csv",
      "size": 59694,
      "updatedAt": "2026-07-08T16:24:03.840Z",
      "ageMs": 2560.30615234375
    },
    "autopilot-qualified-contactable-leads.csv": {
      "exists": true,
      "path": "C:\\Users\\steve\\bd-lead-engine\\autopilot-qualified-contactable-leads.csv",
      "size": 59694,
      "updatedAt": "2026-07-08T16:24:03.854Z",
      "ageMs": 2546.305908203125
    },
    "autopilot-hot-leads.csv": {
      "exists": true,
      "path": "C:\\Users\\steve\\bd-lead-engine\\autopilot-hot-leads.csv",
      "size": 46126,
      "updatedAt": "2026-07-08T16:24:03.866Z",
      "ageMs": 2535.306884765625
    },
    "autopilot-working-leads.csv": {
      "exists": true,
      "path": "C:\\Users\\steve\\bd-lead-engine\\autopilot-working-leads.csv",
      "size": 95286,
      "updatedAt": "2026-07-08T16:24:05.577Z",
      "ageMs": 824.4423828125
    },
    "autopilot-social-leads.csv": {
      "exists": true,
      "path": "C:\\Users\\steve\\bd-lead-engine\\autopilot-social-leads.csv",
      "size": 49849,
      "updatedAt": "2026-07-08T16:24:05.547Z",
      "ageMs": 854.443603515625
    },
    "autopilot-linkedin-leads.csv": {
      "exists": true,
      "path": "C:\\Users\\steve\\bd-lead-engine\\autopilot-linkedin-leads.csv",
      "size": 48699,
      "updatedAt": "2026-07-08T16:24:05.555Z",
      "ageMs": 846.442626953125
    },
    "autopilot-instagram-leads.csv": {
      "exists": true,
      "path": "C:\\Users\\steve\\bd-lead-engine\\autopilot-instagram-leads.csv",
      "size": 482,
      "updatedAt": "2026-07-08T16:24:05.550Z",
      "ageMs": 851.443115234375
    },
    "autopilot-x-leads.csv": {
      "exists": true,
      "path": "C:\\Users\\steve\\bd-lead-engine\\autopilot-x-leads.csv",
      "size": 482,
      "updatedAt": "2026-07-08T16:24:05.558Z",
      "ageMs": 843.443603515625
    }
  },
  "recentRuns": [
    {
      "id": "run_1783264963896",
      "startedAt": "2026-07-05T15:22:43.896Z",
      "finishedAt": "2026-07-05T15:40:43.601Z",
      "settings": {
        "limitPerQuery": 12,
        "maxQueries": 220,
        "fetchPages": true,
        "deepEnrich": true,
        "searchContacts": true,
        "queryOffset": 22480,
        "includePartners": true,
        "includeRecruitment": true,
        "includeIntentPosts": true,
        "includeEcosystem": true,
        "includeSocialProfiles": true,
        "includeForums": true,
        "includeSpecialistSources": true,
        "includeYouTube": false,
        "regionSet": "global",
        "delayMs": 6500,
        "queryOffsetBase": 15000,
        "maxCycles": 0,
        "maxContactPages": 5,
        "maxExternalWebsites": 4,
        "maxTrailQueries": 16,
        "trailLimit": 6,
        "exportEvery": 3,
        "incremental": true,
        "onlyIntents": "",
        "onlyChannels": "myfxbook,mql5,specialist"
      },
      "totalQueries": 48,
      "rawResults": 0,
      "leadsFound": 0,
      "created": 0,
      "updated": 0,
      "sourceStats": {
        "myfxbook": {
          "searches": 19,
          "raw": 0,
          "qualified": 0,
          "saved": 0,
          "discarded": 0,
          "duplicates": 0,
          "errors": 0,
          "providerErrors": 112,
          "reasons": {
            "provider_errors": 28
          }
        },
        "mql5": {
          "searches": 19,
          "raw": 0,
          "qualified": 0,
          "saved": 0,
          "discarded": 0,
          "duplicates": 0,
          "errors": 0,
          "providerErrors": 112,
          "reasons": {
            "provider_errors": 28
          }
        },
        "specialist": {
          "searches": 10,
          "raw": 0,
          "qualified": 0,
          "saved": 0,
          "discarded": 0,
          "duplicates": 0,
          "errors": 0,
          "providerErrors": 72,
          "reasons": {
            "provider_errors": 18
          }
        }
      },
      "qualifiedBySource": {},
      "exportResult": {
        "csvPath": "C:\\Users\\steve\\bd-lead-engine\\autopilot-leads.csv",
        "jsonPath": "C:\\Users\\steve\\bd-lead-engine\\autopilot-leads.json",
        "contactCsvPath": null,
        "contactJsonPath": null,
        "hotCsvPath": null,
        "hotJsonPath": null,
        "socialCsvPath": "C:\\Users\\steve\\bd-lead-engine\\autopilot-social-leads.csv",
        "socialJsonPath": "C:\\Users\\steve\\bd-lead-engine\\autopilot-social-leads.json",
        "instagramCsvPath": "C:\\Users\\steve\\bd-lead-engine\\autopilot-instagram-leads.csv",
        "instagramJsonPath": "C:\\Users\\steve\\bd-lead-engine\\autopilot-instagram-leads.json",
        "linkedinCsvPath": "C:\\Users\\steve\\bd-lead-engine\\autopilot-linkedin-leads.csv",
        "linkedinJsonPath": "C:\\Users\\steve\\bd-lead-engine\\autopilot-linkedin-leads.json",
        "xCsvPath": "C:\\Users\\steve\\bd-lead-engine\\autopilot-x-leads.csv",
        "xJsonPath": "C:\\Users\\steve\\bd-lead-engine\\autopilot-x-leads.json",
        "workingCsvPath": "C:\\Users\\steve\\bd-lead-engine\\autopilot-working-leads.csv",
        "workingJsonPath": "C:\\Users\\steve\\bd-lead-engine\\autopilot-working-leads.json",
        "researchCsvPath": "C:\\Users\\steve\\bd-lead-engine\\autopilot-research-sources.csv",
        "researchJsonPath": "C:\\Users\\steve\\bd-lead-engine\\autopilot-research-sources.json",
        "exported": 107,
        "working": 131,
        "researchSources": 135,
        "contactable": 107,
        "hot": 49,
        "social": 43,
        "instagram": 4,
        "linkedin": 27,
        "x": 6,
        "total": 1438
      },
      "errors": []
    },
    {
      "id": "run_1783262387543",
      "startedAt": "2026-07-05T14:39:47.543Z",
      "finishedAt": "2026-07-05T15:40:35.673Z",
      "settings": {
        "limitPerQuery": 10,
        "maxQueries": 150,
        "fetchPages": true,
        "deepEnrich": true,
        "searchContacts": true,
        "queryOffset": 4350,
        "includePartners": true,
        "includeRecruitment": true,
        "includeIntentPosts": true,
        "includeEcosystem": true,
        "includeSocialProfiles": true,
        "includeForums": true,
        "includeSpecialistSources": true,
        "includeYouTube": false,
        "regionSet": "global",
        "delayMs": 5500,
        "queryOffsetBase": 3000,
        "maxCycles": 0,
        "maxContactPages": 7,
        "maxExternalWebsites": 6,
        "maxTrailQueries": 24,
        "trailLimit": 8,
        "exportEvery": 3,
        "incremental": true,
        "onlyIntents": "social",
        "onlyChannels": ""
      },
      "totalQueries": 145,
      "rawResults": 189,
      "leadsFound": 10,
      "created": 3,
      "updated": 7,
      "sourceStats": {
        "linkedin": {
          "searches": 50,
          "raw": 24,
          "qualified": 1,
          "saved": 0,
          "discarded": 1,
          "duplicates": 23,
          "errors": 0,
          "providerErrors": 251,
          "reasons": {
            "provider_errors": 63,
            "hard_rejected": 1
          }
        },
        "instagram": {
          "searches": 31,
          "raw": 70,
          "qualified": 1,
          "saved": 0,
          "discarded": 1,
          "duplicates": 69,
          "errors": 0,
          "providerErrors": 176,
          "reasons": {
            "provider_errors": 44,
            "hard_rejected": 1
          }
        },
        "x": {
          "searches": 22,
          "raw": 53,
          "qualified": 3,
          "saved": 2,
          "discarded": 2,
          "duplicates": 49,
          "errors": 0,
          "providerErrors": 139,
          "reasons": {
            "provider_errors": 35,
            "hard_rejected": 2
          }
        },
        "telegram": {
          "searches": 11,
          "raw": 0,
          "qualified": 0,
          "saved": 0,
          "discarded": 0,
          "duplicates": 0,
          "errors": 0,
          "providerErrors": 88,
          "reasons": {
            "provider_errors": 22
          }
        },
        "discord": {
          "searches": 6,
          "raw": 2,
          "qualified": 0,
          "saved": 0,
          "discarded": 1,
          "duplicates": 1,
          "errors": 0,
          "providerErrors": 47,
          "reasons": {
            "provider_errors": 12,
            "hard_rejected": 1
          }
        },
        "tiktok": {
          "searches": 14,
          "raw": 40,
          "qualified": 5,
          "saved": 1,
          "discarded": 7,
          "duplicates": 32,
          "errors": 0,
          "providerErrors": 103,
          "reasons": {
            "provider_errors": 26,
            "hard_rejected": 7
          }
        },
        "facebook_threads": {
          "searches": 5,
          "raw": 0,
          "qualified": 0,
          "saved": 0,
          "discarded": 0,
          "duplicates": 0,
          "errors": 0,
          "providerErrors": 40,
          "reasons": {
            "provider_errors": 10
          }
        },
        "web": {
          "searches": 6,
          "raw": 0,
          "qualified": 0,
          "saved": 0,
          "discarded": 0,
          "duplicates": 0,
          "errors": 0,
          "providerErrors": 48,
          "reasons": {
            "provider_errors": 12
          }
        }
      },
      "qualifiedBySource": {
        "instagram": 1,
        "linkedin": 3,
        "tiktok": 4,
        "mql5": 1,
        "x": 1
      },
      "exportResult": {
        "csvPath": "C:\\Users\\steve\\bd-lead-engine\\autopilot-leads.csv",
        "jsonPath": "C:\\Users\\steve\\bd-lead-engine\\autopilot-leads.json",
        "contactCsvPath": null,
        "contactJsonPath": null,
        "hotCsvPath": null,
        "hotJsonPath": null,
        "socialCsvPath": "C:\\Users\\steve\\bd-lead-engine\\autopilot-social-leads.csv",
        "socialJsonPath": "C:\\Users\\steve\\bd-lead-engine\\autopilot-social-leads.json",
        "instagramCsvPath": "C:\\Users\\steve\\bd-lead-engine\\autopilot-instagram-leads.csv",
        "instagramJsonPath": "C:\\Users\\steve\\bd-lead-engine\\autopilot-instagram-leads.json",
        "linkedinCsvPath": "C:\\Users\\steve\\bd-lead-engine\\autopilot-linkedin-leads.csv",
        "linkedinJsonPath": "C:\\Users\\steve\\bd-lead-engine\\autopilot-linkedin-leads.json",
        "xCsvPath": "C:\\Users\\steve\\bd-lead-engine\\autopilot-x-leads.csv",
        "xJsonPath": "C:\\Users\\steve\\bd-lead-engine\\autopilot-x-leads.json",
        "workingCsvPath": "C:\\Users\\steve\\bd-lead-engine\\autopilot-working-leads.csv",
        "workingJsonPath": "C:\\Users\\steve\\bd-lead-engine\\autopilot-working-leads.json",
        "researchCsvPath": "C:\\Users\\steve\\bd-lead-engine\\autopilot-research-sources.csv",
        "researchJsonPath": "C:\\Users\\steve\\bd-lead-engine\\autopilot-research-sources.json",
        "exported": 107,
        "working": 131,
        "researchSources": 135,
        "contactable": 107,
        "hot": 49,
        "social": 43,
        "instagram": 4,
        "linkedin": 27,
        "x": 6,
        "total": 1438
      },
      "errors": []
    },
    {
      "id": "run_1783259472039",
      "startedAt": "2026-07-05T13:51:12.039Z",
      "finishedAt": "2026-07-05T15:35:07.831Z",
      "settings": {
        "limitPerQuery": 12,
        "maxQueries": 160,
        "fetchPages": true,
        "deepEnrich": true,
        "searchContacts": true,
        "queryOffset": 18800,
        "includePartners": true,
        "includeRecruitment": true,
        "includeIntentPosts": true,
        "includeEcosystem": true,
        "includeSocialProfiles": true,
        "includeForums": true,
        "includeSpecialistSources": true,
        "includeYouTube": false,
        "regionSet": "global",
        "delayMs": 6500,
        "queryOffsetBase": 18000,
        "maxCycles": 0,
        "maxContactPages": 5,
        "maxExternalWebsites": 4,
        "maxTrailQueries": 16,
        "trailLimit": 6,
        "exportEvery": 3,
        "incremental": true,
        "onlyIntents": "",
        "onlyChannels": "ecosystem,recruitment"
      },
      "totalQueries": 160,
      "rawResults": 1334,
      "leadsFound": 32,
      "created": 9,
      "updated": 24,
      "sourceStats": {
        "ecosystem": {
          "searches": 69,
          "raw": 501,
          "qualified": 2,
          "saved": 1,
          "discarded": 47,
          "duplicates": 452,
          "errors": 0,
          "providerErrors": 549,
          "reasons": {
            "provider_errors": 138,
            "hard_rejected": 47
          }
        },
        "recruitment": {
          "searches": 91,
          "raw": 833,
          "qualified": 30,
          "saved": 8,
          "discarded": 103,
          "duplicates": 722,
          "errors": 0,
          "providerErrors": 362,
          "reasons": {
            "provider_errors": 91,
            "hard_rejected": 103
          }
        }
      },
      "qualifiedBySource": {
        "linkedin": 1,
        "instagram": 1,
        "recruitment": 25,
        "forum": 2,
        "x": 1,
        "ecosystem": 1,
        "tradingview": 1
      },
      "exportResult": {
        "csvPath": "C:\\Users\\steve\\bd-lead-engine\\autopilot-leads.csv",
        "jsonPath": "C:\\Users\\steve\\bd-lead-engine\\autopilot-leads.json",
        "contactCsvPath": null,
        "contactJsonPath": null,
        "hotCsvPath": null,
        "hotJsonPath": null,
        "socialCsvPath": "C:\\Users\\steve\\bd-lead-engine\\autopilot-social-leads.csv",
        "socialJsonPath": "C:\\Users\\steve\\bd-lead-engine\\autopilot-social-leads.json",
        "instagramCsvPath": "C:\\Users\\steve\\bd-lead-engine\\autopilot-instagram-leads.csv",
        "instagramJsonPath": "C:\\Users\\steve\\bd-lead-engine\\autopilot-instagram-leads.json",
        "linkedinCsvPath": "C:\\Users\\steve\\bd-lead-engine\\autopilot-linkedin-leads.csv",
        "linkedinJsonPath": "C:\\Users\\steve\\bd-lead-engine\\autopilot-linkedin-leads.json",
        "xCsvPath": "C:\\Users\\steve\\bd-lead-engine\\autopilot-x-leads.csv",
        "xJsonPath": "C:\\Users\\steve\\bd-lead-engine\\autopilot-x-leads.json",
        "workingCsvPath": "C:\\Users\\steve\\bd-lead-engine\\autopilot-working-leads.csv",
        "workingJsonPath": "C:\\Users\\steve\\bd-lead-engine\\autopilot-working-leads.json",
        "researchCsvPath": "C:\\Users\\steve\\bd-lead-engine\\autopilot-research-sources.csv",
        "researchJsonPath": "C:\\Users\\steve\\bd-lead-engine\\autopilot-research-sources.json",
        "exported": 108,
        "working": 131,
        "researchSources": 134,
        "contactable": 108,
        "hot": 49,
        "social": 44,
        "instagram": 5,
        "linkedin": 27,
        "x": 6,
        "total": 1438
      },
      "errors": []
    },
    {
      "id": "run_1783261589361",
      "startedAt": "2026-07-05T14:26:29.361Z",
      "finishedAt": "2026-07-05T15:34:24.980Z",
      "settings": {
        "limitPerQuery": 12,
        "maxQueries": 220,
        "fetchPages": true,
        "deepEnrich": true,
        "searchContacts": true,
        "queryOffset": 13760,
        "includePartners": true,
        "includeRecruitment": true,
        "includeIntentPosts": true,
        "includeEcosystem": true,
        "includeSocialProfiles": true,
        "includeForums": true,
        "includeSpecialistSources": true,
        "includeYouTube": false,
        "regionSet": "global",
        "delayMs": 6500,
        "queryOffsetBase": 12000,
        "maxCycles": 0,
        "maxContactPages": 5,
        "maxExternalWebsites": 4,
        "maxTrailQueries": 16,
        "trailLimit": 6,
        "exportEvery": 3,
        "incremental": true,
        "onlyIntents": "",
        "onlyChannels": "linkedin"
      },
      "totalQueries": 199,
      "rawResults": 54,
      "leadsFound": 1,
      "created": 0,
      "updated": 1,
      "sourceStats": {
        "linkedin": {
          "searches": 199,
          "raw": 54,
          "qualified": 1,
          "saved": 0,
          "discarded": 1,
          "duplicates": 53,
          "errors": 0,
          "providerErrors": 1111,
          "reasons": {
            "provider_errors": 279,
            "hard_rejected": 1
          }
        }
      },
      "qualifiedBySource": {
        "linkedin": 1
      },
      "exportResult": {
        "csvPath": "C:\\Users\\steve\\bd-lead-engine\\autopilot-leads.csv",
        "jsonPath": "C:\\Users\\steve\\bd-lead-engine\\autopilot-leads.json",
        "contactCsvPath": null,
        "contactJsonPath": null,
        "hotCsvPath": null,
        "hotJsonPath": null,
        "socialCsvPath": "C:\\Users\\steve\\bd-lead-engine\\autopilot-social-leads.csv",
        "socialJsonPath": "C:\\Users\\steve\\bd-lead-engine\\autopilot-social-leads.json",
        "instagramCsvPath": "C:\\Users\\steve\\bd-lead-engine\\autopilot-instagram-leads.csv",
        "instagramJsonPath": "C:\\Users\\steve\\bd-lead-engine\\autopilot-instagram-leads.json",
        "linkedinCsvPath": "C:\\Users\\steve\\bd-lead-engine\\autopilot-linkedin-leads.csv",
        "linkedinJsonPath": "C:\\Users\\steve\\bd-lead-engine\\autopilot-linkedin-leads.json",
        "xCsvPath": "C:\\Users\\steve\\bd-lead-engine\\autopilot-x-leads.csv",
        "xJsonPath": "C:\\Users\\steve\\bd-lead-engine\\autopilot-x-leads.json",
        "workingCsvPath": "C:\\Users\\steve\\bd-lead-engine\\autopilot-working-leads.csv",
        "workingJsonPath": "C:\\Users\\steve\\bd-lead-engine\\autopilot-working-leads.json",
        "researchCsvPath": "C:\\Users\\steve\\bd-lead-engine\\autopilot-research-sources.csv",
        "researchJsonPath": "C:\\Users\\steve\\bd-lead-engine\\autopilot-research-sources.json",
        "exported": 108,
        "working": 131,
        "researchSources": 134,
        "contactable": 108,
        "hot": 48,
        "social": 44,
        "instagram": 5,
        "linkedin": 27,
        "x": 6,
        "total": 1438
      },
      "errors": []
    },
    {
      "id": "run_1783263914728",
      "startedAt": "2026-07-05T15:05:14.728Z",
      "finishedAt": "2026-07-05T15:22:36.120Z",
      "settings": {
        "limitPerQuery": 12,
        "maxQueries": 220,
        "fetchPages": true,
        "deepEnrich": true,
        "searchContacts": true,
        "queryOffset": 22260,
        "includePartners": true,
        "includeRecruitment": true,
        "includeIntentPosts": true,
        "includeEcosystem": true,
        "includeSocialProfiles": true,
        "includeForums": true,
        "includeSpecialistSources": true,
        "includeYouTube": false,
        "regionSet": "global",
        "delayMs": 6500,
        "queryOffsetBase": 15000,
        "maxCycles": 0,
        "maxContactPages": 5,
        "maxExternalWebsites": 4,
        "maxTrailQueries": 16,
        "trailLimit": 6,
        "exportEvery": 3,
        "incremental": true,
        "onlyIntents": "",
        "onlyChannels": "myfxbook,mql5,specialist"
      },
      "totalQueries": 48,
      "rawResults": 0,
      "leadsFound": 0,
      "created": 0,
      "updated": 0,
      "sourceStats": {
        "myfxbook": {
          "searches": 19,
          "raw": 0,
          "qualified": 0,
          "saved": 0,
          "discarded": 0,
          "duplicates": 0,
          "errors": 0,
          "providerErrors": 112,
          "reasons": {
            "provider_errors": 28
          }
        },
        "mql5": {
          "searches": 19,
          "raw": 0,
          "qualified": 0,
          "saved": 0,
          "discarded": 0,
          "duplicates": 0,
          "errors": 0,
          "providerErrors": 112,
          "reasons": {
            "provider_errors": 28
          }
        },
        "specialist": {
          "searches": 10,
          "raw": 0,
          "qualified": 0,
          "saved": 0,
          "discarded": 0,
          "duplicates": 0,
          "errors": 0,
          "providerErrors": 72,
          "reasons": {
            "provider_errors": 18
          }
        }
      },
      "qualifiedBySource": {},
      "exportResult": {
        "csvPath": "C:\\Users\\steve\\bd-lead-engine\\autopilot-leads.csv",
        "jsonPath": "C:\\Users\\steve\\bd-lead-engine\\autopilot-leads.json",
        "contactCsvPath": null,
        "contactJsonPath": null,
        "hotCsvPath": null,
        "hotJsonPath": null,
        "socialCsvPath": "C:\\Users\\steve\\bd-lead-engine\\autopilot-social-leads.csv",
        "socialJsonPath": "C:\\Users\\steve\\bd-lead-engine\\autopilot-social-leads.json",
        "instagramCsvPath": "C:\\Users\\steve\\bd-lead-engine\\autopilot-instagram-leads.csv",
        "instagramJsonPath": "C:\\Users\\steve\\bd-lead-engine\\autopilot-instagram-leads.json",
        "linkedinCsvPath": "C:\\Users\\steve\\bd-lead-engine\\autopilot-linkedin-leads.csv",
        "linkedinJsonPath": "C:\\Users\\steve\\bd-lead-engine\\autopilot-linkedin-leads.json",
        "xCsvPath": "C:\\Users\\steve\\bd-lead-engine\\autopilot-x-leads.csv",
        "xJsonPath": "C:\\Users\\steve\\bd-lead-engine\\autopilot-x-leads.json",
        "workingCsvPath": "C:\\Users\\steve\\bd-lead-engine\\autopilot-working-leads.csv",
        "workingJsonPath": "C:\\Users\\steve\\bd-lead-engine\\autopilot-working-leads.json",
        "researchCsvPath": "C:\\Users\\steve\\bd-lead-engine\\autopilot-research-sources.csv",
        "researchJsonPath": "C:\\Users\\steve\\bd-lead-engine\\autopilot-research-sources.json",
        "exported": 107,
        "working": 131,
        "researchSources": 133,
        "contactable": 107,
        "hot": 46,
        "social": 43,
        "instagram": 5,
        "linkedin": 26,
        "x": 6,
        "total": 1433
      },
      "errors": []
    }
  ],
  "pruneHistory": [
    {
      "at": "2026-07-07T02:57:14.029Z",
      "reason": "lead-cleaner",
      "removed": 1,
      "before": 121,
      "after": 120,
      "byReason": {
        "non_financial_platform_noise": 1
      },
      "backupPath": "C:\\Users\\steve\\bd-lead-engine\\data\\leads.prune-backup-2026-07-07T02-57-14-028Z.json"
    },
    {
      "at": "2026-07-07T02:55:43.563Z",
      "reason": "lead-cleaner",
      "removed": 1,
      "before": 121,
      "after": 120,
      "byReason": {
        "non_financial_platform_noise": 1
      },
      "backupPath": "C:\\Users\\steve\\bd-lead-engine\\data\\leads.prune-backup-2026-07-07T02-55-43-562Z.json"
    },
    {
      "at": "2026-07-07T02:46:42.769Z",
      "reason": "lead-cleaner",
      "removed": 1,
      "before": 121,
      "after": 120,
      "byReason": {
        "generic_platform_page": 1
      },
      "backupPath": "C:\\Users\\steve\\bd-lead-engine\\data\\leads.prune-backup-2026-07-07T02-46-42-768Z.json"
    },
    {
      "at": "2026-07-07T02:28:41.706Z",
      "reason": "lead-cleaner",
      "removed": 1,
      "before": 121,
      "after": 120,
      "byReason": {
        "generic_platform_page": 1
      },
      "backupPath": "C:\\Users\\steve\\bd-lead-engine\\data\\leads.prune-backup-2026-07-07T02-28-41-705Z.json"
    },
    {
      "at": "2026-07-07T02:24:11.152Z",
      "reason": "lead-cleaner",
      "removed": 1,
      "before": 121,
      "after": 120,
      "byReason": {
        "non_financial_platform_noise": 1
      },
      "backupPath": "C:\\Users\\steve\\bd-lead-engine\\data\\leads.prune-backup-2026-07-07T02-24-11-151Z.json"
    }
  ],
  "cleanupHistory": [
    {
      "at": "2026-07-05T00:45:41.075Z",
      "reason": "cli",
      "removed": 22,
      "before": 1220,
      "after": 1198,
      "byReason": {
        "event_exhibitor_list_not_target": 21,
        "tradingview_not_target_lead": 1
      },
      "backupPath": "C:\\Users\\steve\\bd-lead-engine\\data\\leads.strict-cleanup-backup-2026-07-05T00-45-41-072Z.json"
    },
    {
      "at": "2026-07-05T00:40:03.094Z",
      "reason": "cli",
      "removed": 17,
      "before": 1242,
      "after": 1225,
      "byReason": {
        "tradingview_not_target_lead": 15,
        "sports_reference_noise": 1,
        "payments_platform_noise": 1
      },
      "backupPath": "C:\\Users\\steve\\bd-lead-engine\\data\\leads.strict-cleanup-backup-2026-07-05T00-40-03-090Z.json"
    }
  ],
  "qualityRebuildHistory": [
    {
      "at": "2026-07-05T16:48:48.359Z",
      "platformContactsRemoved": 18,
      "reclassified": 704,
      "samples": [
        {
          "name": "@Lukebnco",
          "before": "",
          "after": "contact@nourtrades.com"
        },
        {
          "name": "@forexsignalroom",
          "before": "",
          "after": "info@forexsignalroom.com"
        },
        {
          "name": "@wayond",
          "before": "",
          "after": "info@wayond.ae"
        },
        {
          "name": "@forexbrokerbostonmerchantf9007",
          "before": "",
          "after": "support@bmfn.com"
        },
        {
          "name": "Análise do Banco Best 2026: opiniões, comissões e produtos | Rankia",
          "before": "",
          "after": "contato@rankia.pt"
        },
        {
          "name": "UK Global Health Summit 2026 - Global Health Partnerships",
          "before": "",
          "after": "louise.mcgrath@globalhealthpartnerships.org"
        },
        {
          "name": "Compassion UK",
          "before": "",
          "after": "blowingthewhistle@compassionuk.org"
        },
        {
          "name": "Compassion Australia – Child Sponsorship | Christian Charity",
          "before": "",
          "after": "compassion@compassion.com.au"
        }
      ]
    }
  ],
  "smartTrailBoostHistory": [],
  "logs": {
    "source-harvester": {
      "out": [
        "[source-harvester cycle 1] Starting quality discovery with 120 queries",
        "[source-harvester cycle 1] Starting quality discovery with 120 queries",
        "[source-harvester cycle 1] Starting quality discovery with 120 queries",
        "[source-harvester cycle 1] Saved qualified lead: Brokerage Review",
        "[source-harvester cycle 1] Starting quality discovery with 120 queries",
        "[source-harvester cycle 1] Starting quality discovery with 120 queries",
        "[source-harvester cycle 1] Starting quality discovery with 120 queries",
        "[source-harvester cycle 1] Starting quality discovery with 120 queries"
      ],
      "err": []
    },
    "source-harvester-social": {
      "out": [
        "[source-harvester-social cycle 1] Saved qualified lead: Badshah Broking",
        "[source-harvester-social cycle 1] Saved qualified lead: reel DK7nfCvhFDa",
        "[source-harvester-social cycle 1] Starting quality discovery with 120 queries",
        "[source-harvester-social cycle 1] Saved qualified lead: Instagram photos and videos",
        "[source-harvester-social cycle 1] Saved qualified lead: Badshah Broking",
        "[source-harvester-social cycle 1] Saved qualified lead: reel DK7nfCvhFDa",
        "[source-harvester-social cycle 1] Starting quality discovery with 120 queries",
        "[source-harvester-social cycle 1] Starting quality discovery with 120 queries"
      ],
      "err": []
    },
    "source-harvester-specialist": {
      "out": [
        "[source-harvester-specialist cycle 1] Saved qualified lead: lilo org",
        "[source-harvester-specialist cycle 1] Starting quality discovery with 120 queries",
        "[source-harvester-specialist cycle 1] Saved qualified lead: company murenamobile",
        "[source-harvester-specialist cycle 1] Saved qualified lead: lilo org",
        "[source-harvester-specialist cycle 1] Starting quality discovery with 120 queries",
        "[source-harvester-specialist cycle 1] Saved qualified lead: company murenamobile",
        "[source-harvester-specialist cycle 1] Saved qualified lead: lilo org",
        "[source-harvester-specialist cycle 1] Starting quality discovery with 120 queries"
      ],
      "err": []
    },
    "source-harvester-ecosystem": {
      "out": [
        "[source-harvester-ecosystem cycle 1] Saved qualified lead: forexexpodubai kudotrade",
        "[source-harvester-ecosystem cycle 1] Saved qualified lead: Yang Lin on LinkedIn Register",
        "[source-harvester-ecosystem cycle 1] Saved qualified lead: I m excited to share that I will be attending the Forex Expo Dubai on ...",
        "[source-harvester-ecosystem cycle 1] Saved qualified lead: Attending Forex Expo Dubai and also being one of the ...",
        "[source-harvester-ecosystem cycle 1] Saved qualified lead: The countdown has begun. The Forex Expo Dubai is set to kick off in",
        "[source-harvester-ecosystem cycle 1] Saved qualified lead: Attending the Forex Expo in Dubai soon and wondering how you",
        "[source-harvester-ecosystem cycle 1] Starting quality discovery with 90 queries",
        "[source-harvester-ecosystem cycle 1] Starting quality discovery with 90 queries"
      ],
      "err": []
    },
    "source-harvester-linkedin": {
      "out": [
        "[source-harvester-linkedin cycle 1] Starting quality discovery with 180 queries",
        "[source-harvester-linkedin cycle 1] Starting quality discovery with 180 queries",
        "[source-harvester-linkedin cycle 1] Starting quality discovery with 180 queries",
        "[source-harvester-linkedin cycle 1] Starting quality discovery with 180 queries",
        "[source-harvester-linkedin cycle 1] Starting quality discovery with 180 queries",
        "[source-harvester-linkedin cycle 1] Starting quality discovery with 180 queries",
        "[source-harvester-linkedin cycle 1] Starting quality discovery with 180 queries",
        "[source-harvester-linkedin cycle 1] Starting quality discovery with 180 queries"
      ],
      "err": []
    },
    "source-harvester-instagram": {
      "out": [
        "[source-harvester-instagram cycle 1] Starting quality discovery with 45 queries",
        "[source-harvester-instagram cycle 1] Starting quality discovery with 45 queries",
        "[source-harvester-instagram cycle 1] Starting quality discovery with 45 queries",
        "[source-harvester-instagram cycle 1] Starting quality discovery with 45 queries",
        "[source-harvester-instagram cycle 1] Starting quality discovery with 45 queries",
        "[source-harvester-instagram cycle 1] Starting quality discovery with 45 queries",
        "[source-harvester-instagram cycle 1] Starting quality discovery with 45 queries",
        "[source-harvester-instagram cycle 1] Starting quality discovery with 45 queries"
      ],
      "err": []
    },
    "source-harvester-platforms": {
      "out": [
        "[source-harvester-platforms cycle 1] Saved qualified lead: users ajtrader2014FTA",
        "[source-harvester-platforms cycle 1] Saved qualified lead: golbagoltrade seller",
        "[source-harvester-platforms cycle 1] Saved qualified lead: 01 xauusd 01",
        "[source-harvester-platforms cycle 1] Starting quality discovery with 47 queries",
        "[source-harvester-platforms cycle 1] Saved qualified lead: users ajtrader2014FTA",
        "[source-harvester-platforms cycle 1] Saved qualified lead: golbagoltrade seller",
        "[source-harvester-platforms cycle 1] Saved qualified lead: 01 xauusd 01",
        "[source-harvester-platforms cycle 1] Starting quality discovery with 47 queries"
      ],
      "err": []
    },
    "source-harvester-communities": {
      "out": [
        "[source-harvester-communities cycle 1] Saved qualified lead: any good brokerages r Forex",
        "[source-harvester-communities cycle 1] Saved qualified lead: What platforms do you use r Forex",
        "[source-harvester-communities cycle 1] Saved qualified lead: r Forex Community",
        "[source-harvester-communities cycle 1] Saved qualified lead: Forex",
        "[source-harvester-communities cycle 1] Saved qualified lead: Broker recommendations with low spreads and good leverage r Forex",
        "[source-harvester-communities cycle 1] Saved qualified lead: r Forex Community",
        "[source-harvester-communities cycle 1] Saved qualified lead: Recommended Broker For a beginner r Forex",
        "[source-harvester-communities cycle 1] Starting quality discovery with 116 queries"
      ],
      "err": []
    },
    "source-harvester-events": {
      "out": [
        "[source-harvester-events cycle 1] Saved qualified lead: Opere com a Tickmill",
        "[source-harvester-events cycle 1] Saved qualified lead: TradingView",
        "[source-harvester-events cycle 1] Saved qualified lead: TradingView Track All",
        "[source-harvester-events cycle 1] Starting quality discovery with 120 queries",
        "[source-harvester-events cycle 1] Saved qualified lead: Opere com a Tickmill",
        "[source-harvester-events cycle 1] Saved qualified lead: TradingView",
        "[source-harvester-events cycle 1] Saved qualified lead: TradingView Track All",
        "[source-harvester-events cycle 1] Starting quality discovery with 120 queries"
      ],
      "err": []
    },
    "enrichment-worker": {
      "out": [
        "[enrichment-worker] stored contactless_due c0f8565297aba88c Exness; emails=0; links=0; makers=0; best=-",
        "[enrichment-worker] stored contactless_due 6eb3193891ee59d8 Forexany good brokerages r Forex; emails=0; links=0; makers=0; best=-",
        "[enrichment-worker] stored contactless_due fe88972c03bce86a ForexRecommended Broker For a beginner r Forex; emails=0; links=0; makers=0; best=-",
        "[enrichment-worker] stored contactless_due 842bcd3ef7edb14c MetaTrader 4; emails=0; links=0; makers=0; best=-",
        "[enrichment-worker] stored contactless_due ca621c264fd26568 Introduction to CFD Basics; emails=0; links=0; makers=0; best=-",
        "[enrichment-worker] stored scheduled_due ab3e54de5c2d8a2e Kumar; emails=0; links=0; makers=6; best=https://in.linkedin.com/in/avinash-kumar-253527281",
        "[enrichment-worker] Started with {\"delayMs\":4500,\"idleMs\":9000,\"staleHours\":8,\"hotStaleHours\":1.5,\"contactlessStaleHours\":1.5,\"rotationHours\":3,\"maxContactPages\":7,\"maxExternalWebsites\":6,\"maxTrailQueries\":18,\"trailLimit\":7}",
        "[enrichment-worker] stored contactless_due ea9e014f6f428d8b Attending the Money Expo at the Jio Convention Centre ...; emails=0; links=0; makers=0; best=https://www.linkedin.com/posts/deepjyoti-dutta-dd11022003_attending-the-money-expo-at-the-jio-convention-activity-7366762448424460289-CzkY"
      ],
      "err": []
    },
    "smart-enrichment-worker": {
      "out": [],
      "err": []
    },
    "contact-gap-worker": {
      "out": [],
      "err": []
    },
    "lead-cleaner": {
      "out": [
        "[lead-cleaner] 2026-07-07T01:52:39.182Z removed=1 totalRemoved=11",
        "[lead-cleaner] 2026-07-07T02:09:10.195Z removed=1 totalRemoved=12",
        "[lead-cleaner] 2026-07-07T02:22:41.095Z removed=1 totalRemoved=13",
        "[lead-cleaner] 2026-07-07T02:24:11.559Z removed=1 totalRemoved=14",
        "[lead-cleaner] 2026-07-07T02:28:42.102Z removed=1 totalRemoved=15",
        "[lead-cleaner] 2026-07-07T02:46:43.205Z removed=1 totalRemoved=16",
        "[lead-cleaner] 2026-07-07T02:55:43.968Z removed=1 totalRemoved=17",
        "[lead-cleaner] 2026-07-07T02:57:14.448Z removed=1 totalRemoved=18"
      ],
      "err": []
    },
    "qualified-exporter": {
      "out": [
        "[qualified-exporter] 2026-07-07T02:53:17.442Z total=120 qualified=27 contactable=27 hot=21 social=23 instagram=1 linkedin=21 x=0",
        "[qualified-exporter] 2026-07-07T02:54:47.847Z total=120 qualified=27 contactable=27 hot=21 social=23 instagram=1 linkedin=21 x=0",
        "[qualified-exporter] 2026-07-07T02:56:18.258Z total=121 qualified=27 contactable=27 hot=21 social=23 instagram=1 linkedin=21 x=0",
        "[qualified-exporter] 2026-07-07T02:57:48.716Z total=120 qualified=27 contactable=27 hot=21 social=23 instagram=1 linkedin=21 x=0",
        "[qualified-exporter] 2026-07-07T02:59:19.149Z total=120 qualified=27 contactable=27 hot=21 social=23 instagram=1 linkedin=21 x=0",
        "[qualified-exporter] 2026-07-07T03:00:49.617Z total=120 qualified=27 contactable=27 hot=21 social=23 instagram=1 linkedin=21 x=0",
        "[qualified-exporter] 2026-07-07T03:02:19.999Z total=120 qualified=27 contactable=27 hot=21 social=23 instagram=1 linkedin=21 x=0",
        "[qualified-exporter] 2026-07-08T16:24:03.942Z total=82 qualified=23 contactable=23 hot=19 social=21 instagram=0 linkedin=20 x=0"
      ],
      "err": [
        "[qualified-exporter] 2026-07-05T22:54:39.472Z SyntaxError: Unterminated string in JSON at position 521902 (line 9214 column 21)",
        "    at JSON.parse (<anonymous>)",
        "    at readDb (file:///C:/Users/steve/bd-lead-engine/src/store.js:31:17)",
        "    at async exportLeads (file:///C:/Users/steve/bd-lead-engine/src/exporter.js:379:14)",
        "    at async runOnce (file:///C:/Users/steve/bd-lead-engine/src/qualified-exporter.js:26:18)",
        "    at async file:///C:/Users/steve/bd-lead-engine/src/qualified-exporter.js:43:5"
      ]
    },
    "ui-snapshot-worker": {
      "out": [
        "[ui-snapshot] ok total=82 rejected=38 buildMs=101",
        "[ui-snapshot] ok total=82 rejected=38 buildMs=100",
        "[ui-snapshot] ok total=82 rejected=38 buildMs=113",
        "[ui-snapshot] ok total=82 rejected=38 buildMs=108",
        "[ui-snapshot] ok total=82 rejected=38 buildMs=102",
        "[ui-snapshot] ok total=82 rejected=38 buildMs=97",
        "[ui-snapshot] ok total=82 rejected=38 buildMs=99",
        "[ui-snapshot] ok total=57 rejected=25 buildMs=126"
      ],
      "err": [
        "[ui-snapshot] Error: EPERM: operation not permitted, rename 'C:\\Users\\steve\\bd-lead-engine\\public\\ui-dashboard.json.31880.1783310997093.tmp' -> 'C:\\Users\\steve\\bd-lead-engine\\public\\ui-dashboard.json'",
        "    at async Object.rename (node:internal/fs/promises:781:10)",
        "    at async writeJsonAtomic (file:///C:/Users/steve/bd-lead-engine/src/ui-snapshot.js:123:3)",
        "    at async buildUiSnapshot (file:///C:/Users/steve/bd-lead-engine/src/ui-snapshot.js:150:3)",
        "    at async loop (file:///C:/Users/steve/bd-lead-engine/src/ui-snapshot.js:159:24)"
      ]
    },
    "cloud-logger-worker": {
      "out": [],
      "err": []
    },
    "supervisor": {
      "out": [
        "[supervisor] 2026-07-07T02:56:31.108Z cycle=145 ok=true raw=121 working=45 a=22",
        "[supervisor] 2026-07-07T02:57:31.416Z cycle=146 ok=true raw=120 working=45 a=22",
        "[supervisor] 2026-07-07T02:58:31.776Z cycle=147 ok=true raw=120 working=45 a=22",
        "[supervisor] 2026-07-07T02:59:32.074Z cycle=148 ok=true raw=120 working=45 a=22",
        "[supervisor] 2026-07-07T03:00:32.359Z cycle=149 ok=true raw=120 working=45 a=22",
        "[supervisor] 2026-07-07T03:01:32.870Z cycle=150 ok=true raw=120 working=45 a=22",
        "[supervisor] 2026-07-07T03:02:34.535Z cycle=151 ok=true raw=120 working=45 a=22",
        "[supervisor] 2026-07-08T16:24:04.109Z cycle=1 ok=true raw=82 working=40 a=20 issues=source-harvester_stale_status,source-harvester-social_stale_status,source-harvester-specialist_stale_status,source-harvester-ecosystem_stale_status,source-harvester-linkedin_stale_status,source-harvester-instagram_stale_status,source-harvester-platforms_stale_status,source-harvester-communities_stale_status,source-harvester-events_stale_status,enrichment-worker_stale_status,smart-enrichment-worker_stale_status,contact-gap-worker_stale_status"
      ],
      "err": []
    },
    "engine-control": {
      "out": [],
      "err": []
    }
  }
}
